README.md
setup.py
pyautodrive/__init__.py
pyautodrive/drive.py
pygta_data_collector.egg-info/PKG-INFO
pygta_data_collector.egg-info/SOURCES.txt
pygta_data_collector.egg-info/dependency_links.txt
pygta_data_collector.egg-info/requires.txt
pygta_data_collector.egg-info/top_level.txt