Metadata-Version: 2.1
Name: pygta-data-collector
Version: 0.0.1
Summary: Collecting images for GTA sel-driving car project
Author: MrKubul (Jakub Dryka)
Author-email: <szanowac@dziekana.com
Keywords: python,gta,ai,deep learning,dataset,dziekan
Classifier: Development Status :: 1 - Planning
Classifier: Intended Audience :: Developers
Classifier: Programming Language :: Python :: 3
Classifier: Operating System :: Unix
Classifier: Operating System :: MacOS :: MacOS X
Classifier: Operating System :: Microsoft :: Windows
